signalstats1090/__init__.py
signalstats1090/__main__.py
signalstats1090/_version.py
signalstats1090/index.html
signalstats1090/signalstats1090.py
signalstats1090-0.9.0.dist-info/entry_points.txt
signalstats1090-0.9.0.dist-info/licenses/LICENSE.md
signalstats1090-0.9.0.dist-info/WHEEL
signalstats1090-0.9.0.dist-info/METADATA
signalstats1090-0.9.0.dist-info/RECORD
