Metadata-Version: 2.4
Name: signalstats1090
Version: 0.9.0
Summary: Signal statistics dashboard for Mode-S/ADS-B signals from dump1090
Author-email: Clemens Vasters <clemensv@microsoft.com>
Requires-Python: >=3.10
Classifier: Programming Language :: Python :: 3
Classifier: License :: OSI Approved :: MIT License
Classifier: Operating System :: OS Independent
License-File: LICENSE.md
Requires-Dist: websockets >= 14.2
Requires-Dist: fastapi >=  0.115.6
Requires-Dist: uvicorn[standard] >= 0.34.0
Requires-Dist: pyModeS >= 2.19
Requires-Dist: psutil >= 6.1.0
